frshodan/__init__.py
frshodan/frshodan.py
frshodan/frshodan_cmd.py
frshodan-0.1.1.dist-info/LICENSE
frshodan-0.1.1.dist-info/METADATA
frshodan-0.1.1.dist-info/WHEEL
frshodan-0.1.1.dist-info/entry_points.txt
frshodan-0.1.1.dist-info/top_level.txt
frshodan-0.1.1.dist-info/RECORD
