Metadata-Version: 2.1
Name: frshodan
Version: 0.1.1
Summary: A library for querying Shodan IP addresses with no API key.
Home-page: https://github.com/LavedenC1/frshodan
Author: Thomas Haddad
Author-email: haddad.thomas19@gmail.com
License: MIT
Classifier: Programming Language :: Python :: 3
Classifier: License :: OSI Approved :: MIT License
Classifier: Operating System :: OS Independent
Requires-Python: >=3.6
License-File: LICENSE
Requires-Dist: beautifulsoup4
Requires-Dist: requests
